[
    {
      "question": "What is Joan's favorite color",
      "options": [
        "Red",
        "Green",
        "Blue",
        "Orange"
      ],
      "answer": "Red"
    },
    {
      "question": "How old is Joan",
      "options": [
        32,
        53,
        24,
        22
      ],
      "answer": 22
    },
    {
      "question": "What is the terminal velocity of an unladen swallow",
      "options": [
        84,
        32,
        69,
        108
      ],
      "answer": 108
    }
  ]